fastapi_resume/__init__.py
fastapi_resume/cli.py
fastapi_resume/exceptions.py
fastapi_resume/py.typed
fastapi_resume/responses.py
fastapi_resume/utils.py
fastapi_resume/api/__init__.py
fastapi_resume/api/basic.py
fastapi_resume/api/contact.py
fastapi_resume/api/education.py
fastapi_resume/api/experience.py
fastapi_resume/api/health.py
fastapi_resume/api/projects.py
fastapi_resume/api/search.py
fastapi_resume/api/skills.py
fastapi_resume-0.0.3.dist-info/licenses/AUTHORS
fastapi_resume-0.0.3.dist-info/licenses/LICENSE
fastapi_resume-0.0.3.dist-info/METADATA
fastapi_resume-0.0.3.dist-info/WHEEL
fastapi_resume-0.0.3.dist-info/entry_points.txt
fastapi_resume-0.0.3.dist-info/top_level.txt
fastapi_resume-0.0.3.dist-info/RECORD
