Metadata-Version: 2.4
Name: fastapi-resume
Version: 0.0.3
Summary: FastAPI-powered resume generator: expose your CV as a JSON REST API
Maintainer-email: Nick Kelly <nialexanderke@proton.me>
Project-URL: Homepage, https://github.com/nickatnight/fastapi-resume
Project-URL: Issues, https://github.com/nickatnight/fastapi-resume/issues
Keywords: Python,resume,project directory,package,packaging,FastAPI,Typer,CLI
Classifier: Development Status :: 4 - Beta
Classifier: Environment :: Console
Classifier: Framework :: FastAPI
Classifier: Intended Audience :: Developers
Classifier: Natural Language :: English
Classifier: Programming Language :: Python :: 3
Classifier: Programming Language :: Python :: 3.10
Classifier: Programming Language :: Python :: 3.11
Classifier: Programming Language :: Python :: 3.12
Classifier: Programming Language :: Python :: 3.13
Classifier: Typing :: Typed
Requires-Python: >=3.12
License-File: LICENSE
License-File: AUTHORS
Requires-Dist: fastapi==0.116.1
Requires-Dist: orjson==3.11.0
Requires-Dist: pyyaml==6.0.2
Requires-Dist: typer==0.16.0
Requires-Dist: uvicorn[standard]==0.32.1
Dynamic: license-file
